airscraper/__init__.py
airscraper/airscraper.py
airscraper-0.1.4.dist-info/LICENSE
airscraper-0.1.4.dist-info/METADATA
airscraper-0.1.4.dist-info/WHEEL
airscraper-0.1.4.dist-info/entry_points.txt
airscraper-0.1.4.dist-info/top_level.txt
airscraper-0.1.4.dist-info/RECORD
