Metadata-Version: 2.1
Name: airscraper
Version: 0.1.4
Summary: Airtable Download CSV helper
Home-page: https://github.com/banditelol/airscraper
Author: Aditya Rachman Putra
Author-email: adityarputra@gmail.com
License: UNKNOWN
Platform: UNKNOWN
Classifier: Programming Language :: Python :: 3
Classifier: License :: OSI Approved :: MIT License
Classifier: Operating System :: OS Independent
License-File: LICENSE
Requires-Dist: beautifulsoup4
Requires-Dist: pandas
